MANIFEST.in
README.rst
setup.py
microschema/__init__.py
microschema/core.py
microschema/tests.py
microschema.egg-info/PKG-INFO
microschema.egg-info/SOURCES.txt
microschema.egg-info/dependency_links.txt
microschema.egg-info/not-zip-safe
microschema.egg-info/top_level.txt