Metadata-Version: 1.1
Name: microschema
Version: 0.5
Summary: MicroSchema is a schema validation library for Python.
Home-page: http://github.com/amibiz/microschema
Author: Ami E. Bizamcher
Author-email: ami.bizamcher@gmail.com
License: BSD
Keywords: microschema schema validate validation validator micro
Platform: UNKNOWN
Classifier: Development Status :: 5 - Production/Stable
Classifier: Intended Audience :: Developers
Classifier: License :: OSI Approved :: BSD License
Classifier: Operating System :: OS Independent
Classifier: Programming Language :: Python
Classifier: Topic :: Software Development :: Libraries :: Python Modules
